taiga_contrib_google_auth
tests
