Metadata-Version: 1.1
Name: taiga-contrib-google-auth2
Version: 0.3
Summary: The Taiga plugin for google authentication
Home-page: https://github.com/seyriz/taiga-contrib-google-auth
Author: HanWool Lee
Author-email: kudnya@gmail.com
License: AGPL
Keywords: taiga,google,auth,plugin
Platform: UNKNOWN
Classifier: Programming Language :: Python
Classifier: Development Status :: 3 - Alpha
Classifier: Framework :: Django
Classifier: Intended Audience :: Developers
Classifier: License :: OSI Approved :: GNU Affero General Public License v3
Classifier: Operating System :: OS Independent
Classifier: Programming Language :: Python
Classifier: Topic :: Internet :: WWW/HTTP
